djangocms_oidc/__init__.py
djangocms_oidc/apps.py
djangocms_oidc/auth.py
djangocms_oidc/cms_plugins.py
djangocms_oidc/constants.py
djangocms_oidc/forms.py
djangocms_oidc/helpers.py
djangocms_oidc/middleware.py
djangocms_oidc/models.py
djangocms_oidc/urls.py
djangocms_oidc/utils.py
djangocms_oidc/views.py
djangocms_oidc/widgets.py
djangocms_oidc/admin/__init__.py
djangocms_oidc/admin/forms.py
djangocms_oidc/admin/options.py
djangocms_oidc/locale/cs/LC_MESSAGES/django.mo
djangocms_oidc/locale/cs/LC_MESSAGES/django.po
djangocms_oidc/migrations/0001_initial.py
djangocms_oidc/migrations/0002_30274_button_label.py
djangocms_oidc/migrations/__init__.py
djangocms_oidc/templates/djangocms_oidc/display_dedicated_content.html
djangocms_oidc/templates/djangocms_oidc/handover_data.html
djangocms_oidc/templates/djangocms_oidc/list_identifiers.html
djangocms_oidc/templates/djangocms_oidc/login.html
djangocms_oidc/templates/djangocms_oidc/show_attribute.html
djangocms_oidc/templates/djangocms_oidc/show_attribute_country.html
djangocms_oidc/templates/djangocms_oidc/change_form/consumer.html
djangocms_oidc/templates/djangocms_oidc/change_form/display_dedicated_content.html
djangocms_oidc/templates/djangocms_oidc/change_form/list_identifiers.html
djangocms_oidc-5.1.0.dist-info/licenses/LICENSE
djangocms_oidc-5.1.0.dist-info/METADATA
djangocms_oidc-5.1.0.dist-info/WHEEL
djangocms_oidc-5.1.0.dist-info/top_level.txt
djangocms_oidc-5.1.0.dist-info/RECORD
