Metadata-Version: 2.4
Name: djangocms-oidc
Version: 5.1.0
Summary: Plugin OIDC (OpenID Connect) into Django CMS.
Home-page: https://github.com/CZ-NIC/djangocms-oidc
Author: Zdeněk Böhm
Author-email: zdenek.bohm@nic.cz
License: GPL GNU License
Platform: OS Independent
Classifier: Development Status :: 5 - Production/Stable
Classifier: Environment :: Web Environment
Classifier: Intended Audience :: Developers
Classifier: License :: OSI Approved :: GNU General Public License (GPL)
Classifier: Operating System :: OS Independent
Classifier: Programming Language :: Python
Classifier: Programming Language :: Python :: 3.10
Classifier: Programming Language :: Python :: 3.12
Classifier: Topic :: Internet :: WWW/HTTP :: Dynamic Content
Classifier: Topic :: Software Development
Classifier: Topic :: Software Development :: Libraries :: Application Frameworks
Classifier: Framework :: Django CMS :: 4.1
Classifier: Framework :: Django CMS :: 5.0
Requires-Python: >=3.10
License-File: LICENSE
Requires-Dist: django-cms<6,>=4.1
Requires-Dist: mozilla-django-oidc~=3.0
Requires-Dist: django-countries~=7.5
Requires-Dist: django-multiselectfield
Provides-Extra: quality
Requires-Dist: isort; extra == "quality"
Requires-Dist: flake8; extra == "quality"
Provides-Extra: test
Requires-Dist: requests_mock; extra == "test"
Requires-Dist: freezegun; extra == "test"
Dynamic: author
Dynamic: author-email
Dynamic: classifier
Dynamic: description
Dynamic: description-content-type
Dynamic: home-page
Dynamic: license
Dynamic: license-file
Dynamic: platform
Dynamic: provides-extra
Dynamic: requires-dist
Dynamic: requires-python
Dynamic: summary
